<annotation>
	<folder>02AfrinEtiketlenmis</folder>
	<filename>02afrinDozerYoluKapatiyor_frame_150.jpg</filename>
	<path>C:\Users\Gokhan GOK\Documents\teknofest\02AfrinEtiketlenmis\02afrinDozerYoluKapatiyor_frame_150.jpg</path>
	<source>
		<database>Unknown</database>
	</source>
	<size>
		<width>640</width>
		<height>360</height>
		<depth>3</depth>
	</size>
	<segmented>0</segmented>
	<object>
		<name>insan</name>
		<pose>Unspecified</pose>
		<truncated>0</truncated>
		<difficult>0</difficult>
		<bndbox>
			<xmin>230</xmin>
			<ymin>141</ymin>
			<xmax>250</xmax>
			<ymax>166</ymax>
		</bndbox>
	</object>
	<object>
		<name>insan</name>
		<pose>Unspecified</pose>
		<truncated>0</truncated>
		<difficult>0</difficult>
		<bndbox>
			<xmin>170</xmin>
			<ymin>204</ymin>
			<xmax>199</xmax>
			<ymax>233</ymax>
		</bndbox>
	</object>
	<object>
		<name>insan</name>
		<pose>Unspecified</pose>
		<truncated>0</truncated>
		<difficult>0</difficult>
		<bndbox>
			<xmin>304</xmin>
			<ymin>94</ymin>
			<xmax>325</xmax>
			<ymax>128</ymax>
		</bndbox>
	</object>
	<object>
		<name>insan</name>
		<pose>Unspecified</pose>
		<truncated>0</truncated>
		<difficult>0</difficult>
		<bndbox>
			<xmin>354</xmin>
			<ymin>215</ymin>
			<xmax>376</xmax>
			<ymax>248</ymax>
		</bndbox>
	</object>
	<object>
		<name>insan</name>
		<pose>Unspecified</pose>
		<truncated>0</truncated>
		<difficult>0</difficult>
		<bndbox>
			<xmin>487</xmin>
			<ymin>311</ymin>
			<xmax>502</xmax>
			<ymax>338</ymax>
		</bndbox>
	</object>
	<object>
		<name>insan</name>
		<pose>Unspecified</pose>
		<truncated>0</truncated>
		<difficult>0</difficult>
		<bndbox>
			<xmin>433</xmin>
			<ymin>299</ymin>
			<xmax>453</xmax>
			<ymax>329</ymax>
		</bndbox>
	</object>
</annotation>
