<annotation verified="yes">
                                    <folder>Annotation</folder>
                                    <filename>afrinvur_frame_1</filename>
                                    <path>E:\Teknofest\output\TensorPascal\JPEGImages\afrinvur_frame_1.jpg</path>
                                    <source>
                                        <database>Unknown</database>
                                    </source>
                                    <size>
                                        <width>1280</width>
                                        <height>720</height>
                                        <depth>3</depth>
                                    </size>
                                    <segmented>0</segmented>
                                    <object>
                                            <name>bina</name>
                                            <pose>Unspecified</pose>
                                            <truncated>0</truncated>
                                            <difficult>0</difficult>
                                            <bndbox>
                                                <xmin>81.53417015341701</xmin>
                                                <ymin>209.7629009762901</ymin>
                                                <xmax>191.32496513249652</xmax>
                                                <ymax>332.0502092050209</ymax>
                                            </bndbox>
                                    </object>
                                    
                                    <object>
                                            <name>arac</name>
                                            <pose>Unspecified</pose>
                                            <truncated>0</truncated>
                                            <difficult>0</difficult>
                                            <bndbox>
                                                <xmin>607.2803347280335</xmin>
                                                <ymin>417.74058577405856</ymin>
                                                <xmax>622.4546722454672</xmax>
                                                <ymax>447.1966527196653</ymax>
                                            </bndbox>
                                    </object>
                                    
                                    <object>
                                            <name>bina</name>
                                            <pose>Unspecified</pose>
                                            <truncated>0</truncated>
                                            <difficult>0</difficult>
                                            <bndbox>
                                                <xmin>872.3849372384938</xmin>
                                                <ymin>332.9428172942817</ymin>
                                                <xmax>1033.0543933054394</xmax>
                                                <ymax>493.6122733612273</ymax>
                                            </bndbox>
                                    </object>
                                    
                                    <object>
                                            <name>bina</name>
                                            <pose>Unspecified</pose>
                                            <truncated>0</truncated>
                                            <difficult>0</difficult>
                                            <bndbox>
                                                <xmin>206.49930264993026</xmin>
                                                <ymin>321.3389121338912</ymin>
                                                <xmax>373.1101813110181</xmax>
                                                <ymax>410.5997210599721</ymax>
                                            </bndbox>
                                    </object>
                                    
                                    <object>
                                            <name>bina</name>
                                            <pose>Unspecified</pose>
                                            <truncated>0</truncated>
                                            <difficult>0</difficult>
                                            <bndbox>
                                                <xmin>363.59832635983264</xmin>
                                                <ymin>416.84797768479774</ymin>
                                                <xmax>566.2203626220363</xmax>
                                                <ymax>530.2092050209205</ymax>
                                            </bndbox>
                                    </object>
                                    
                                    <object>
                                            <name>bina</name>
                                            <pose>Unspecified</pose>
                                            <truncated>0</truncated>
                                            <difficult>0</difficult>
                                            <bndbox>
                                                <xmin>333.24965132496516</xmin>
                                                <ymin>107.11297071129707</ymin>
                                                <xmax>548.36820083682</xmax>
                                                <ymax>270.46025104602506</ymax>
                                            </bndbox>
                                    </object>
                                    
                                    <object>
                                            <name>bina</name>
                                            <pose>Unspecified</pose>
                                            <truncated>0</truncated>
                                            <difficult>0</difficult>
                                            <bndbox>
                                                <xmin>775.9832635983264</xmin>
                                                <ymin>4.463040446304045</ymin>
                                                <xmax>908.0892608089262</xmax>
                                                <ymax>124.96513249651325</ymax>
                                            </bndbox>
                                    </object>
                                    
                                    <object>
                                            <name>bina</name>
                                            <pose>Unspecified</pose>
                                            <truncated>0</truncated>
                                            <difficult>0</difficult>
                                            <bndbox>
                                                <xmin>1093.7517433751743</xmin>
                                                <ymin>198.15899581589957</ymin>
                                                <xmax>1260.6694560669457</xmax>
                                                <ymax>281.17154811715477</ymax>
                                            </bndbox>
                                    </object>
                                    
                                    <object>
                                            <name>bina</name>
                                            <pose>Unspecified</pose>
                                            <truncated>0</truncated>
                                            <difficult>0</difficult>
                                            <bndbox>
                                                <xmin>659.9442119944212</xmin>
                                                <ymin>495.39748953974896</ymin>
                                                <xmax>753.6680613668061</xmax>
                                                <ymax>588.2287308228731</ymax>
                                            </bndbox>
                                    </object>
                                    </annotation>