<annotation verified="yes">
                                    <folder>Annotation</folder>
                                    <filename>afrinvur_frame_43</filename>
                                    <path>E:\Teknofest\output\TensorPascal\JPEGImages\afrinvur_frame_43.jpg</path>
                                    <source>
                                        <database>Unknown</database>
                                    </source>
                                    <size>
                                        <width>1280</width>
                                        <height>720</height>
                                        <depth>3</depth>
                                    </size>
                                    <segmented>0</segmented>
                                    <object>
                                            <name>insan</name>
                                            <pose>Unspecified</pose>
                                            <truncated>0</truncated>
                                            <difficult>0</difficult>
                                            <bndbox>
                                                <xmin>604.6025104602511</xmin>
                                                <ymin>278.4937238493724</ymin>
                                                <xmax>645.6624825662483</xmax>
                                                <ymax>365.07670850767084</ymax>
                                            </bndbox>
                                    </object>
                                    
                                    <object>
                                            <name>insan</name>
                                            <pose>Unspecified</pose>
                                            <truncated>0</truncated>
                                            <difficult>0</difficult>
                                            <bndbox>
                                                <xmin>583.7656903765691</xmin>
                                                <ymin>311.52022315202237</ymin>
                                                <xmax>620.6694560669456</xmax>
                                                <ymax>408.81450488145055</ymax>
                                            </bndbox>
                                    </object>
                                    
                                    <object>
                                            <name>arac</name>
                                            <pose>Unspecified</pose>
                                            <truncated>0</truncated>
                                            <difficult>0</difficult>
                                            <bndbox>
                                                <xmin>297.54532775453276</xmin>
                                                <ymin>296.34588563458857</ymin>
                                                <xmax>579.302649930265</xmax>
                                                <ymax>485.5788005578801</ymax>
                                            </bndbox>
                                    </object>
                                    </annotation>