<annotation>
	<folder>hadi_hayirlisi</folder>
	<filename>T190619_V4_K1-3835-frame2484.jpg</filename>
	<path>/Users/Burakhan/Backups/teknofest/research/object_detection/edu/hadi_hayirlisi/T190619_V4_K1-3835-frame2484.jpg</path>
	<source>
		<database>Unknown</database>
	</source>
	<size>
		<width>1920</width>
		<height>900</height>
		<depth>3</depth>
	</size>
	<segmented>0</segmented>
	<object>
		<name>araba</name>
		<pose>Unspecified</pose>
		<truncated>0</truncated>
		<difficult>0</difficult>
		<bndbox>
			<xmin>142</xmin>
			<ymin>226</ymin>
			<xmax>210</xmax>
			<ymax>269</ymax>
		</bndbox>
	</object>
	<object>
		<name>araba</name>
		<pose>Unspecified</pose>
		<truncated>0</truncated>
		<difficult>0</difficult>
		<bndbox>
			<xmin>762</xmin>
			<ymin>277</ymin>
			<xmax>843</xmax>
			<ymax>335</ymax>
		</bndbox>
	</object>
	<object>
		<name>araba</name>
		<pose>Unspecified</pose>
		<truncated>0</truncated>
		<difficult>0</difficult>
		<bndbox>
			<xmin>1837</xmin>
			<ymin>351</ymin>
			<xmax>1903</xmax>
			<ymax>398</ymax>
		</bndbox>
	</object>
</annotation>
