<annotation>
	<folder>yenietiket</folder>
	<filename>video3frame9240.jpg</filename>
	<path>E:\yenietiket\video3frame9240.jpg</path>
	<source>
		<database>Unknown</database>
	</source>
	<size>
		<width>1920</width>
		<height>900</height>
		<depth>3</depth>
	</size>
	<segmented>0</segmented>
	<object>
		<name>arac</name>
		<pose>Unspecified</pose>
		<truncated>0</truncated>
		<difficult>0</difficult>
		<bndbox>
			<xmin>301</xmin>
			<ymin>137</ymin>
			<xmax>369</xmax>
			<ymax>204</ymax>
		</bndbox>
	</object>
	<object>
		<name>arac</name>
		<pose>Unspecified</pose>
		<truncated>0</truncated>
		<difficult>0</difficult>
		<bndbox>
			<xmin>259</xmin>
			<ymin>212</ymin>
			<xmax>303</xmax>
			<ymax>281</ymax>
		</bndbox>
	</object>
	<object>
		<name>arac</name>
		<pose>Unspecified</pose>
		<truncated>0</truncated>
		<difficult>0</difficult>
		<bndbox>
			<xmin>509</xmin>
			<ymin>454</ymin>
			<xmax>592</xmax>
			<ymax>517</ymax>
		</bndbox>
	</object>
</annotation>
